apps/__apps__.py
apps/__init__.py
cli/__init__.py
cli/cli_commands.py
cli/cli_console.py
exceptions/__init__.py
exceptions/api_exceptions.py
exceptions/db_exceptions.py
exceptions/file_exceptions.py
utils/__init__.py
utils/_dl.py
utils/_signal.py
utils/_singleton.py
utils/abogus.py
utils/conf_manager.py
utils/decorators.py
utils/json_filter.py
utils/utils.py
utils/xbogus.py
pureff-0.1.3.dist-info/METADATA
pureff-0.1.3.dist-info/WHEEL
pureff-0.1.3.dist-info/entry_points.txt
pureff-0.1.3.dist-info/top_level.txt
pureff-0.1.3.dist-info/RECORD
